README.rst
setup.py
ConcurrentEvents.egg-info/PKG-INFO
ConcurrentEvents.egg-info/SOURCES.txt
ConcurrentEvents.egg-info/dependency_links.txt
ConcurrentEvents.egg-info/top_level.txt
concurrentevents/__init__.py
concurrentevents/_exceptions.py
concurrentevents/catch.py
concurrentevents/eventmanager.py
concurrentevents/enums/__init__.py
concurrentevents/tools/__init__.py
concurrentevents/tools/resourcepool.py
concurrentevents/tools/threadmonitor.py