Metadata-Version: 2.1
Name: ConcurrentEvents
Version: 1.12.3
Summary: An event system build on top of the concurrent futures library, including additional threading tools
Home-page: https://gitlab.com/Reggles44/concurrentevents
Author: Reggles
Author-email: reginaldbeakes@gmail.com
License: UNKNOWN
Platform: UNKNOWN
Classifier: Programming Language :: Python :: 3
Classifier: Operating System :: OS Independent
